ytlisten_proj/__init__.py
ytlisten_proj/ytlisten.py
ytlisten-0.24.dist-info/LICENSE.md
ytlisten-0.24.dist-info/METADATA
ytlisten-0.24.dist-info/WHEEL
ytlisten-0.24.dist-info/entry_points.txt
ytlisten-0.24.dist-info/top_level.txt
ytlisten-0.24.dist-info/RECORD
