Metadata-Version: 2.1
Name: ytlisten
Version: 0.24
Summary: A command-line tool to search and listen to YouTube audio
Home-page: https://github.com/ismaelc/ytlisten
Author: Chris Ismael
Author-email: chris.ismael@gmail.com
License: MIT
Classifier: Development Status :: 3 - Alpha
Classifier: License :: OSI Approved :: MIT License
Classifier: Programming Language :: Python :: 3
Classifier: Programming Language :: Python :: 3.6
Classifier: Programming Language :: Python :: 3.7
Classifier: Programming Language :: Python :: 3.8
Classifier: Programming Language :: Python :: 3.9
Classifier: Programming Language :: Python :: Implementation :: CPython
Classifier: Programming Language :: Python :: Implementation :: PyPy
License-File: LICENSE.md
Requires-Dist: pytube
Requires-Dist: python-vlc
Requires-Dist: google-api-python-client
